{
    "actors":  [
                   {
                       "Alignment":  [
                                         0.5,
                                         0.5
                                     ],
                       "Alpha":  1,
                       "Angle":  0,
                       "Flip":  0,
                       "Position":  [
                                        0,
                                        0
                                    ],
                       "Scale":  [
                                     1,
                                     1
                                 ],
                       "Shown":  true,
                       "sprite":  "knight",
                       "type":  1,
                       "uid":  1
                   }
               ],
    "customvariables":  null,
    "events":  null,
    "stageOptions":  {
                         "SpriteInfo":  [
                                            {
                                                "SpriteInfo":  "knight",
                                                "Texture":  "monsters"
                                            }
                                        ],
                         "StageLength":  0.2
                     },
    "timelines":  null
}
